pyscses/__init__.py
pyscses/calculation.py
pyscses/constants.py
pyscses/defect_at_site.py
pyscses/defect_species.py
pyscses/grid.py
pyscses/matrix_solver.py
pyscses/set_of_sites.py
pyscses/set_up_calculation.py
pyscses/site.py
pyscses-1.0.0.dist-info/LICENSE
pyscses-1.0.0.dist-info/METADATA
pyscses-1.0.0.dist-info/WHEEL
pyscses-1.0.0.dist-info/top_level.txt
pyscses-1.0.0.dist-info/RECORD
