Metadata-Version: 2.1
Name: pyscses
Version: 1.0.0
Summary: PYthon Space-Charge Site Explicit Solver
Home-page: https://github.com/bjmorgan/pyscses
Author: Georgina L. Wellock
Author-email: g.l.wellock@bath.ac.uk
License: MIT
Download-URL: https://github.com/bjmorgan/pyscses/archive/1.0.0.tar.gz
Platform: UNKNOWN
Requires-Dist: numpy
Requires-Dist: mpmath
Requires-Dist: scipy
